beancount_mcp/__init__.py
beancount_mcp/__main__.py
beancount_mcp/server.py
beancount_mcp-0.1.1.dist-info/METADATA
beancount_mcp-0.1.1.dist-info/WHEEL
beancount_mcp-0.1.1.dist-info/entry_points.txt
beancount_mcp-0.1.1.dist-info/RECORD
